flake8_ado/__init__.py
flake8_ado/ado_client.py
flake8_ado/checkers.py
flake8_ado/domain.py
flake8_ado/plugin.py
flake8_ado/scanner.py
flake8_ado/validators.py
flake8_ado-0.3.dist-info/entry_points.txt
flake8_ado-0.3.dist-info/WHEEL
flake8_ado-0.3.dist-info/METADATA
flake8_ado-0.3.dist-info/RECORD
