Metadata-Version: 2.1
Name: flake8-ado
Version: 0.3
Summary: Flake8 plugin to check comments against AzureDevOps ticket references.
Home-page: https://github.com/DanielKusyDev/flake8-ado
License: MIT
Keywords: flake8,aod,azure devops,lint
Author: DanielKusyDev
Author-email: daniel.kusy97@gmail.com
Requires-Python: >=3.7,<4.0
Classifier: Intended Audience :: Developers
Classifier: License :: OSI Approved :: MIT License
Classifier: Programming Language :: Python :: 3
Classifier: Programming Language :: Python :: 3.7
Classifier: Programming Language :: Python :: 3.8
Classifier: Programming Language :: Python :: 3.9
Classifier: Programming Language :: Python :: 3.10
Classifier: Programming Language :: Python :: 3.10
Classifier: Programming Language :: Python :: 3.7
Classifier: Programming Language :: Python :: 3.8
Classifier: Programming Language :: Python :: 3.9
Classifier: Topic :: Software Development :: Quality Assurance
Requires-Dist: azure-devops (>=6.0.0-beta.4,<7.0.0)
Requires-Dist: importlib-metadata (==4)
Requires-Dist: pytest-mock (>=3.8.2,<4.0.0)
Requires-Dist: tox (>=3.26.0,<4.0.0)
Project-URL: Repository, https://github.com/DanielKusyDev/flake8-ado
